kqueue
fcntl(F_GETFL): %s
fcntl(F_SETFL,O_NONBLOCK): %s
setsockopt SO_KEEPALIVE: %s
setsockopt SO_SNDBUF: %s
connect: %s
setsockopt TCP_NODELAY: %s
creating socket: %s
setsockopt SO_REUSEADDR: %s
unable to bind socket
setsockopt: %s
bind: %s
listen: %s
accept: %s
d->ht[0].size > (unsigned)d->rehashidx
dict.c
iter->fingerprint == dictFingerprint(iter->d)
setnx
setex
psetex
append
strlen
exists
setbit
getbit
setrange
getrange
substr
incr
decr
mget
rpush
lpush
rpushx
lpushx
linsert
rpop
lpop
brpop
brpoplpush
blpop
llen
lindex
lset
lrange
ltrim
lrem
rpoplpush
sadd
srem
smove
sismember
scard
spop
srandmember
sinter
sinterstore
sunion
sunionstore
sdiff
sdiffstore
smembers
sscan
zadd
zincrby
zrem
zremrangebyscore
zremrangebyrank
zremrangebylex
zunionstore
zinterstore
zrange
zrangebyscore
zrevrangebyscore
zrangebylex
zrevrangebylex
zcount
zlexcount
zrevrange
zcard
zscore
zrank
zrevrank
zscan
hset
hsetnx
hget
hmset
hmget
hincrby
hincrbyfloat
hdel
hlen
hkeys
hvals
hgetall
hexists
hscan
incrby
decrby
incrbyfloat
getset
mset
msetnx
randomkey
select
move
rename
renamenx
expire
expireat
pexpire
pexpireat
keys
scan
dbsize
auth
rslt
ping
echo
save
bgsave
bgrewriteaof
shutdown
arlt
lastsave
type
multi
exec
discard
sync
psync
replconf
arslt
flushdb
flushall
sort
info
monitor
pttl
persist
slaveof
role
last
debug
config
subscribe
rpslt
unsubscribe
psubscribe
punsubscribe
publish
pltr
pubsub
pltrR
watch
unwatch
restore
migrate
dump
client
eval
evalsha
slowlog
script
time
bitop
bitcount
bitpos
pfselftest
pfadd
pfcount
pfmerge
pfdebug
.-*#
%d %b %H:%M:%S.
%03d
[%d] %s %c %s
 | signal handler] (
expired
Closing idle client
SIGTERM received but errors trying to shut down the server, check the logs for more information
DB %d: %lld keys (%lld volatile) in %lld slots HT.
%lu clients connected (%lu slaves), %zu bytes in use
Warning, detected child with unmatched pid: %ld
%d changes in %d seconds. Saving...
Starting automatic rewriting of AOF on %lld%% growth
ln != NULL
redis.c
-ERR
+PONG
+QUEUED
-WRONGTYPE Operation against a key holding the wrong kind of value
-ERR no such key
-ERR syntax error
-ERR source and destination objects are the same
-ERR index out of range
-NOSCRIPT No matching script. Please use EVAL.
-LOADING Redis is loading the dataset in memory
-BUSY Redis is busy running a script. You can only call SCRIPT KILL or SHUTDOWN NOSAVE.
-MASTERDOWN Link with MASTER is down and slave-serve-stale-data is set to 'no'.
-MISCONF Redis is configured to save RDB snapshots, but is currently not able to persist on disk. Commands that may modify the data set are disabled. Please check Redis logs for details about the error.
-READONLY You can't write against a read only slave.
-NOAUTH Authentication required.
-OOM command not allowed when used memory > 'maxmemory'.
-EXECABORT Transaction discarded because of previous errors.
-NOREPLICAS Not enough good slaves to write.
SELECT
message
pmessage
subscribe
unsubscribe
psubscribe
punsubscribe
RPOP
LPOP
LPUSH
minstring
maxstring
redis
/var/run/redis.pid
dump.rdb
appendonly.aof
<no assertion failed>
<no file>
Unable to obtain the current NOFILE limit (%s), assuming 1024 and setting the max clients configuration accordingly.
Your current 'ulimit -n' of %llu is not enough for Redis to start. Please increase your open file limit to at least %llu. Exiting.
You requested maxclients of %d requiring at least %llu max file descriptors.
Redis can't set maximum open files to %llu because of OS error: %s.
Current maximum open files is %llu. maxclients has been reduced to %d to compensate for low ulimit. If you need higher maxclients increase 'ulimit -n'.
Increased maximum number of open files to %llu (it was originally set to %llu).
Creating Server TCP listening socket %s:%d: %s
Opening socket: %s
Configured to not listen anywhere, exiting.
"Can't create the serverCron time event."
"Unrecoverable error creating server.ipfd file event."
"Unrecoverable error creating server.sofd file event."
Can't open the append-only file: %s
Warning: 32 bit instance detected but no memory limit set. Setting 3 GB maxmemory limit with 'noeviction' policy now.
"Unsupported command flag"
retval1 == DICT_OK && retval2 == DICT_OK
quit
unknown command '%s'
wrong number of arguments for '%s' command
-MISCONF Errors writing to the AOF file: %s
only (P)SUBSCRIBE / (P)UNSUBSCRIBE / QUIT allowed in this context
Removing the unix socket file.
User requested shutdown...
There is a child saving an .rdb. Killing it!
Writing initial AOF, can't exit.
There is a child rewriting the AOF. Killing it!
Calling fsync() on the AOF file.
Saving the final RDB snapshot before exiting.
Error trying to save the DB, can't exit.
Removing the pid file.
%s is now ready to exit, bye bye...
Sentinel
Redis
Client sent AUTH, but no password is set
invalid password
%lluB
%.2fK
%.2fM
%.2fG
default
server
sentinel
standalone
# Server
redis_version:%s
redis_git_sha1:%s
redis_git_dirty:%d
redis_build_id:%llx
redis_mode:%s
os:%s %s %s
arch_bits:%d
multiplexing_api:%s
gcc_version:%d.%d.%d
process_id:%ld
run_id:%s
tcp_port:%d
uptime_in_seconds:%jd
uptime_in_days:%jd
hz:%d
lru_clock:%ld
config_file:%s
2.8.12
clients
# Clients
connected_clients:%lu
client_longest_output_list:%lu
client_biggest_input_buf:%lu
blocked_clients:%d
memory
# Memory
used_memory:%zu
used_memory_human:%s
used_memory_rss:%zu
used_memory_peak:%zu
used_memory_peak_human:%s
used_memory_lua:%lld
mem_fragmentation_ratio:%.2f
mem_allocator:%s
libc
persistence
# Persistence
loading:%d
rdb_changes_since_last_save:%lld
rdb_bgsave_in_progress:%d
rdb_last_save_time:%jd
rdb_last_bgsave_status:%s
rdb_last_bgsave_time_sec:%jd
rdb_current_bgsave_time_sec:%jd
aof_enabled:%d
aof_rewrite_in_progress:%d
aof_rewrite_scheduled:%d
aof_last_rewrite_time_sec:%jd
aof_current_rewrite_time_sec:%jd
aof_last_bgrewrite_status:%s
aof_last_write_status:%s
aof_current_size:%lld
aof_base_size:%lld
aof_pending_rewrite:%d
aof_buffer_length:%zu
aof_rewrite_buffer_length:%lu
aof_pending_bio_fsync:%llu
aof_delayed_fsync:%lu
loading_start_time:%jd
loading_total_bytes:%llu
loading_loaded_bytes:%llu
loading_loaded_perc:%.2f
loading_eta_seconds:%jd
stats
# Stats
total_connections_received:%lld
total_commands_processed:%lld
instantaneous_ops_per_sec:%lld
rejected_connections:%lld
sync_full:%lld
sync_partial_ok:%lld
sync_partial_err:%lld
expired_keys:%lld
evicted_keys:%lld
keyspace_hits:%lld
keyspace_misses:%lld
pubsub_channels:%ld
pubsub_patterns:%lu
latest_fork_usec:%lld
replication
# Replication
role:%s
master
slave
master_host:%s
master_port:%d
master_link_status:%s
master_last_io_seconds_ago:%d
master_sync_in_progress:%d
slave_repl_offset:%lld
down
master_sync_left_bytes:%lld
master_sync_last_io_seconds_ago:%d
master_link_down_since_seconds:%jd
slave_priority:%d
slave_read_only:%d
connected_slaves:%lu
min_slaves_good_slaves:%d
wait_bgsave
send_bulk
online
slave%d:ip=%s,port=%d,state=%s,offset=%lld,lag=%ld
master_repl_offset:%lld
repl_backlog_active:%d
repl_backlog_size:%lld
repl_backlog_first_byte_offset:%lld
repl_backlog_histlen:%lld
# CPU
used_cpu_sys:%.2f
used_cpu_user:%.2f
used_cpu_sys_children:%.2f
used_cpu_user_children:%.2f
commandstats
# Commandstats
cmdstat_%s:calls=%lld,usec=%lld,usec_per_call=%.2f
keyspace
# Keyspace
db%d:keys=%lld,expires=%lld,avg_ttl=%lld
$%lu
evicted
/dev/null
Redis server v=%s sha=%s:%d malloc=%s bits=%d build=%llx
Usage: ./redis-server [/path/to/redis.conf] [options]
       ./redis-server - (read config from stdin)
       ./redis-server -v or --version
       ./redis-server -h or --help
       ./redis-server --test-memory <megabytes>
Examples:
       ./redis-server (run the server with default conf)
       ./redis-server /etc/redis/6379.conf
       ./redis-server --port 7777
       ./redis-server --port 7777 --slaveof 127.0.0.1 8888
       ./redis-server /etc/myredis.conf --loglevel verbose
Sentinel mode:
       ./redis-server /etc/sentinel.conf --sentinel
                _._                                                  
           _.-``__ ''-._                                             
      _.-``    `.  `_.  ''-._           Redis %s (%s/%d) %s bit
  .-`` .-```.  ```\/    _.,_ ''-._                                   
 (    '      ,       .-`  | `,    )     Running in %s mode
 |`-._`-...-` __...-.``-._|'` _.-'|     Port: %d
 |    `-._   `._    /     _.-'    |     PID: %ld
  `-._    `-._  `-./  _.-'    _.-'                                   
 |`-._`-._    `-.__.-'    _.-'_.-'|                                  
 |    `-._`-._        _.-'_.-'    |           http://redis.io        
  `-._    `-._`-.__.-'_.-'    _.-'                                   
 |`-._`-._    `-.__.-'    _.-'_.-'|                                  
 |    `-._`-._        _.-'_.-'    |                                  
  `-._    `-._`-.__.-'_.-'    _.-'                                   
      `-._    `-.__.-'    _.-'                                       
          `-._        _.-'                                           
              `-.__.-'                                               
stand alone
redis-sentinel
--sentinel
DB loaded from append only file: %.3f seconds
DB loaded from disk: %.3f seconds
Fatal error loading the DB: %s. Exiting.
Out Of Memory allocating %zu bytes!
"Redis aborting for OUT OF MEMORY"
%s %s:%d
This version of redis-server will not run without arguments.
--version
--help
--test-memory
Please specify the amount of memory to test in megabytes.
Example: ./redis-server --test-memory 4096
Warning: no config file specified, using the default config. In order to specify a config file use %s /path/to/%s.conf
Server started, Redis version 2.8.12
The server is now ready to accept connections on port %d
The server is now ready to accept connections at %s
WARNING: You specified a maxmemory value that is less than 1MB (current value is %llu bytes). Are you sure this is what you really want?
Received SIGTERM, scheduling shutdown...
sdsIncrLen
sds.c
sh->free >= incr
sh->free >= 0
\x%02x
zmalloc: Out of memory trying to allocate %zu bytes
entry.prevrawlen > 0
ziplist.c
NULL
{total bytes %d} {length %u}
{tail offset %u}
{addr 0x%08lx, index %2d, offset %5ld, rl: %5u, hs %2u, pl: %5u, pls: %2u, payload %5u} 
fwrite
%lld
{end}
00000000
       0
2.8.12dt28.sd.apple.com-1592189054       000000000
listLength(reply) > 0
networking.c
"Wrong obj->encoding in addReply()"
-ERR 
*%ld
-inf
Accepting client connection: %s
Accepted %s:%d
Accepted connection to %s
Connection with master lost.
Connection with slave %s:%d lost.
Error writing to client: %s
Protocol error: too big inline request
Protocol error: unbalanced quotes in request
c->argc == 0
Protocol error: too big mbulk count string
c->querybuf[0] == '*'
Protocol error: invalid multibulk length
c->multibulklen > 0
Protocol error: too big bulk count string
Protocol error: expected '$', got '%c'
Protocol error: invalid bulk length
"Unknown request type"
Reading from client: %s
Client closed connection
Closing client that reached max query buffer length: %s (qbuf initial bytes: %s)
[%s]:%d
%s:%d
%s:0
id=%U addr=%s fd=%i name=%s age=%I idle=%I flags=%s db=%i sub=%i psub=%i multi=%i qbuf=%U qbuf-free=%U obl=%U oll=%U omem=%U events=%s cmd=%s
list
kill
Unknown client type '%s'
addr
skipme
No such client
setname
Client names cannot contain spaces, newlines or special characters.
getname
Syntax error, try CLIENT (LIST | KILL ip:port | GETNAME | SETNAME connection-name)
c->cmd != NULL
i < c->argc
normal
c->reply_bytes < ULONG_MAX-(1024*64)
Client %s scheduled to be closed ASAP for overcoming of output buffer limits.
Error registering fd event for the new client: %s (fd=%d)
-ERR max number of clients reached
Protocol error from client: %s
/dev/urandom
%.17Lf
o->encoding == REDIS_ENCODING_RAW
object.c
"Unknown list encoding type"
"Unknown set encoding type"
"Unknown hash encoding type"
"decrRefCount against refcount <= 0"
o->type == REDIS_STRING
"Unknown encoding type"
a->type == REDIS_STRING && b->type == REDIS_STRING
value is not a valid float
value is not an integer or out of range
hashtable
linkedlist
ziplist
intset
skiplist
unknown
refcount
encoding
idletime
Syntax error. Try OBJECT (refcount|encoding|idletime)
retval == REDIS_OK
db.c
de != NULL
invalid DB index
"Type not handled in SCAN callback."
invalid cursor
o == NULL || o->type == REDIS_SET || o->type == REDIS_HASH || o->type == REDIS_ZSET
count
match
"Not handled encoding in SCAN."
rv < sizeof(buf)
none
string
zset
hash
nosave
Errors trying to SHUTDOWN. Check logs.
rename_from
rename_to
dictFind(db->dict,key->ptr) != NULL
kde != NULL
dbDelete(c->db,key)
j < argc
server.repl_backlog == NULL
replication.c
listLength(server.slaves) == 0
!(listLength(slaves) != 0 && server.repl_backlog == NULL)
%ld.%06ld 
[%d lua] 
[%d unix:%s] 
[%d %s] 
"%ld"
[PSYNC] Slave request offset: %lld
[PSYNC] Backlog history len is zero
[PSYNC] Backlog size: %lld
[PSYNC] First byte: %lld
[PSYNC] History len: %lld
[PSYNC] Current index: %lld
[PSYNC] Skipping: %lld
[PSYNC] Index of first byte: %lld
[PSYNC] Reply total length: %lld
[PSYNC] addReply() length: %lld
Partial resynchronization not accepted: Runid mismatch (Client asked for '%s', I'm '%s')
Full resync requested by slave.
Unable to partial resync with the slave for lack of backlog (Slave request was: %lld).
Warning: slave tried to PSYNC with an offset that is greater than the master replication offset.
+CONTINUE
Partial resynchronization request accepted. Sending %lld bytes of backlog starting from offset %lld.
+FULLRESYNC %s %lld
Can't SYNC while not connected with my master
SYNC and PSYNC are invalid with pending output
Slave asks for synchronization
Waiting for end of BGSAVE for SYNC
Waiting for next BGSAVE for SYNC
Starting BGSAVE for SYNC
Replication failed, can't BGSAVE
Unable to perform background save
listening-port
Unrecognized REPLCONF option: %s
$%lld
Read error sending DB to slave: %s
premature EOF
Write error sending DB to slave: %s
Unable to register writable event for slave bulk transfer: %s
Synchronization with slave succeeded
SYNC failed. BGSAVE child returned an error
SYNC failed. Can't open/stat DB after BGSAVE: %s
SYNC failed. BGSAVE failed
server.repl_state == REDIS_REPL_TRANSFER
I/O error reading bulk count from MASTER: %s
MASTER aborted replication with an error: %s
Bad protocol from MASTER, the first byte is not '$' (we received '%s'), are you sure the host and port are right?
MASTER <-> SLAVE sync: receiving %lld bytes from master
I/O error trying to sync with MASTER: %s
connection lost
Write error or short write writing to the DB dump file needed for MASTER <-> SLAVE synchronization: %s
Failed trying to rename the temp DB into dump.rdb in MASTER <-> SLAVE synchronization: %s
MASTER <-> SLAVE sync: Flushing old data
MASTER <-> SLAVE sync: Loading DB in memory
Failed trying to load the MASTER synchronization DB from disk
MASTER <-> SLAVE sync: Finished with success
Failed enabling the AOF after successful master synchronization! Trying it again in one second.
FATAL: this slave instance finished the synchronization with its master, but the AOF can't be turned on. Exiting now.
-Writing to master: %s
-Reading from master: %s
Trying a partial resynchronization (request %s:%s).
Partial resynchronization not possible (no cached master)
PSYNC
+FULLRESYNC
Master replied with wrong +FULLRESYNC syntax.
Full resync from master: %s:%lld
+CONTINUE
Successful partial resynchronization with master.
-ERR
Unexpected reply to PSYNC from master: %s
Master does not support PSYNC or is in error state (reply: %s)
Error condition on socket for SYNC: %s
Non blocking connect for SYNC fired the event.
PING
I/O error reading PING reply from master: %s
-NOAUTH
-ERR operation not permitted
Error reply to PING from master: '%s'
Master replied to PING, replication can continue...
AUTH
Unable to AUTH to MASTER: %s
REPLCONF
(Non critical) Master does not understand REPLCONF listening-port: %s
MASTER <-> SLAVE sync: Master accepted a Partial Resynchronization.
Retrying with SYNC...
SYNC
I/O error writing to MASTER: %s
temp-%d.%ld.rdb
Opening the temp file needed for MASTER <-> SLAVE synchronization: %s
Can't create readable event for SYNC: %s (fd=%d)
Unable to connect to MASTER: %s
Can't create readable event for SYNC
server.repl_state == REDIS_REPL_CONNECTING || server.repl_state == REDIS_REPL_RECEIVE_PONG
MASTER MODE enabled (user request)
SLAVE OF would result into synchronization with the master we are already connected with. No operation performed.
+OK Already connected to specified master
SLAVE OF %s:%d enabled (user request)
connect
connecting
connected
server.master != NULL && server.cached_master == NULL
Caching the disconnected master state.
Discarding previously cached master state.
Error resurrecting the cached master, impossible to add the readable handler: %s
Error resurrecting the cached master, impossible to add the writable handler: %s
retval == DICT_OK
Timeout connecting to the MASTER...
Timeout receiving bulk data from MASTER... If the problem persists try to set the 'repl-timeout' parameter in redis.conf to a larger value.
MASTER timeout: no data nor PING received...
Connecting to MASTER %s:%d
MASTER <-> SLAVE sync started
PING
Disconnecting timedout slave: %s:%d
Replication backlog freed after %d seconds without connected slaves.
"Unknown RDB integer encoding type"
rdb.c
enclen < 32
obj->encoding == REDIS_ENCODING_RAW
"Unknown RDB encoding type"
"Unknown set encoding"
"Unknown hash encoding"
len != -1
temp-%d.rdb
Failed opening .rdb for saving: %s
REDIS%04d
Error moving temp DB file on the final destination: %s
DB saved on disk
Write error saving DB on disk: %s
redis-rdb-bgsave
RDB: %zu MB of memory used by copy-on-write
Can't save in background: fork: %s
Background saving started by pid %d
field->encoding == REDIS_ENCODING_RAW
ret == REDIS_OK
len == 0
"Unknown encoding"
REDIS
Wrong signature trying to load DB from file
Can't handle RDB format version %d
FATAL: Data file was created with a Redis server configured to handle more than %d databases. Exiting
RDB file was saved with checksum disabled: no check performed.
Wrong RDB checksum. Aborting now.
Short read or OOM loading DB. Unrecoverable error, aborting now.
Background saving terminated with success
Background saving error
Background saving terminated by signal %d
Background save already in progress
Can't BGSAVE while AOF log rewriting is in progress
Background saving started
invalid expire time in SETEX
offset is out of range
wrong number of arguments for MSET
increment or decrement would overflow
increment would produce NaN or Infinity
string exceeds maximum allowed size (512MB)
t_list.c
li->subject->encoding == li->encoding
entry->zi != NULL
entry->ln != NULL
subject->type == REDIS_LIST
"Unsupported list conversion"
after
before
"List encoding is not LINKEDLIST nor ZIPLIST!"
dictSize(c->bpop.keys) != 0
l != NULL
dictAdd(db->ready_keys,key,NULL) == DICT_OK
timeout is not an integer or out of range
timeout is negative
value != NULL
listTypeLength(key) > 0
dictAdd(subject->ptr,value,NULL) == DICT_OK
t_set.c
"Unsupported encoding"
setobj->type == REDIS_SET && setobj->encoding == REDIS_ENCODING_INTSET
dictAdd(d,element,NULL) == DICT_OK
"Unsupported set conversion"
SREM
dictSize(d) == size
!isnan(score)
t_zset.c
x != NULL
sptr != NULL
ziplistGet(sptr,&vstr,&vlen,&vlong)
ziplistGet(eptr,&vstr,&vlen,&vlong)
*eptr != NULL && *sptr != NULL
_sptr != NULL
_eptr != NULL
p != NULL
(eptr = ziplistPrev(zl,sptr)) != NULL
ele->encoding == REDIS_ENCODING_RAW
(sptr = ziplistNext(zl,eptr)) != NULL
"Unknown target encoding"
dictAdd(zs->dict,ele,&node->score) == DICT_OK
resulting score is not a number (NaN)
zslDelete(zs->zsl,curscore,curobj)
dictAdd(zs->dict,ele,&znode->score) == DICT_OK
zincr
zslDelete(zs->zsl,score,c->argv[j])
min or max is not a float
min or max not valid string range item
it->zl.sptr != NULL
"Unsupported type"
ziplistGet(it->zl.eptr,&val->estr,&val->elen,&val->ell)
"Unsupported element encoding"
at least 1 input key is needed for ZUNIONSTORE/ZINTERSTORE
weights
weight value is not a float
aggregate
"Unknown operator"
withscores
eptr != NULL && sptr != NULL
limit
zslValueLteMax(score,&range)
zzlLexValueLteMax(eptr,&range)
rank
"Unknown ZUNION/INTER aggregate type"
o->encoding == REDIS_ENCODING_ZIPLIST
t_hash.c
vptr != NULL
o->encoding == REDIS_ENCODING_HT
vptr == NULL
hi->encoding == REDIS_ENCODING_ZIPLIST
hi->encoding == REDIS_ENCODING_HT
ziplist with dup elements dump
ret == DICT_OK
"Not implemented"
wrong number of arguments for HMSET
hash value is not an integer
hash value is not a valid float
HSET
count == length
Unbalanced quotes in configuration line
timeout
Invalid timeout value
tcp-keepalive
Invalid tcp-keepalive value
port
Invalid port
tcp-backlog
Invalid backlog value
bind
Too many bind addresses specified
unixsocket
unixsocketperm
Invalid socket file permissions
Invalid save parameters
Can't chdir to '%s': %s
loglevel
verbose
notice
warning
Invalid log level. Must be one of debug, notice, warning
logfile
Can't open the log file: %s
syslog-enabled
argument must be 'yes' or 'no'
syslog-ident
syslog-facility
Invalid log facility. Must be one of USER or between LOCAL0-LOCAL7
databases
Invalid number of databases
include
maxclients
Invalid max clients limit
maxmemory
maxmemory-policy
volatile-lru
volatile-random
volatile-ttl
allkeys-lru
allkeys-random
noeviction
Invalid maxmemory policy
maxmemory-samples
maxmemory-samples must be 1 or greater
repl-ping-slave-period
repl-ping-slave-period must be 1 or greater
repl-timeout
repl-timeout must be 1 or greater
repl-disable-tcp-nodelay
repl-backlog-size
repl-backlog-size must be 1 or greater.
repl-backlog-ttl
repl-backlog-ttl can't be negative 
masterauth
slave-serve-stale-data
slave-read-only
rdbcompression
rdbchecksum
activerehashing
daemonize
appendonly
appendfilename
appendfilename can't be a path, just a filename
no-appendfsync-on-rewrite
appendfsync
always
everysec
argument must be 'no', 'always' or 'everysec'
auto-aof-rewrite-percentage
Invalid negative percentage for AOF auto rewrite
auto-aof-rewrite-min-size
aof-rewrite-incremental-fsync
requirepass
Password is longer than REDIS_AUTHPASS_MAX_LEN
pidfile
dbfilename
dbfilename can't be a path, just a filename
hash-max-ziplist-entries
hash-max-ziplist-value
list-max-ziplist-entries
list-max-ziplist-value
set-max-intset-entries
zset-max-ziplist-entries
zset-max-ziplist-value
hll-sparse-max-bytes
rename-command
No such command in rename-command
config.c
Target command name already exists
lua-time-limit
slowlog-log-slower-than
slowlog-max-len
client-output-buffer-limit
Unrecognized client limit class
Negative number of seconds in soft limit is invalid
stop-writes-on-bgsave-error
slave-priority
min-slaves-to-write
Invalid value for min-slaves-to-write.
min-slaves-max-lag
Invalid value for min-slaves-max-lag.
notify-keyspace-events
Invalid event class character. Use 'g$lshzxeA'.
sentinel directive while not in sentinel mode
Bad directive or wrong number of arguments
*** FATAL CONFIG FILE ERROR ***
Reading the configuration file, at line %d
>>> '%s'
Fatal error, can't open config file '%s'
c->argv[2]->encoding == REDIS_ENCODING_RAW
c->argv[3]->encoding == REDIS_ENCODING_RAW
WARNING: the new maxmemory value set via CONFIG SET is smaller than the current memory usage. This will result in keys eviction and/or inability to accept new write commands depending on the maxmemory-policy.
The operating system is not able to handle the specified number of clients, try with %d
The event loop API used by Redis is not able to handle the specified number of clients
Unable to turn on AOF. Check server logs.
Changing directory: %s
watchdog-period
Unsupported CONFIG parameter: %s
Invalid argument '%s' for CONFIG SET '%s'
%jd %d
%s %llu %llu %ld
%s %d
# Generated by CONFIG REWRITE
# ??? 
%lldgb
%lldmb
%lldkb
%s %s
%s %lld
%s %o
save %ld %d
%s %s %d
%s %s %s %s %ld
Not rewritten option: %s
resetstat
rewrite
The server is running without a config file
CONFIG REWRITE failed: %s
Rewriting config file: %s
CONFIG REWRITE executed with success.
CONFIG subcommand must be one of GET, SET, RESETSTAT, REWRITE
Wrong number of arguments for CONFIG %s
user
local0
local1
local2
local3
local4
local5
local6
local7
Background AOF buffer size: %lu MB
server.aof_state != REDIS_AOF_OFF
aof.c
Killing running AOF rewrite child: %ld
server.aof_state == REDIS_AOF_OFF
Redis needs to enable the AOF but can't open the append only file: %s
Redis needs to enable the AOF but can't trigger a background AOF rewrite operation. Check the above logs for more info about the error.
Asynchronous AOF fsync is taking too long (disk is busy?). Writing the AOF buffer without waiting for fsync to complete, this may slow down Redis.
Error writing to the AOF file: %s
Short write while writing to the AOF file: (nwritten=%lld, expected=%lld)
Could not remove short write from the append-only file.  Redis may refuse to load the AOF the next time it starts.  ftruncate: %s
Can't recover from AOF write error when the AOF fsync policy is 'always'. Exiting...
AOF write error looks solved, Redis can write again.
PEXPIREAT
SELECT
$%lu
Fatal error: can't open the append log file for reading: %s
Unknown command '%s' reading the append only file
fakeClient->bufpos == 0 && listLength(fakeClient->reply) == 0
(fakeClient->flags & REDIS_BLOCKED) == 0
Unexpected end of file reading the append only file
Unrecoverable error reading the append only file: %s
Bad file format reading the append only file: make a backup of your AOF file, then use ./redis-check-aof --fix <filename>
"Unknown string encoding"
RPUSH
"Unknown list encoding"
SADD
ziplistGet(eptr,&vstr,&vlen,&vll)
ZADD
"Unknown sorted zset encoding"
HMSET
temp-rewriteaof-%d.aof
Opening the temp file for AOF rewrite in rewriteAppendOnlyFile(): %s
SELECT
PEXPIREAT
Error moving temp append only file on the final destination: %s
SYNC append only file rewrite performed
Write error writing append only file on disk: %s
redis-aof-rewrite
temp-rewriteaof-bg-%d.aof
AOF rewrite: %zu MB of memory used by copy-on-write
Can't rewrite append only file in background: fork: %s
Background append only file rewriting started by pid %d
Background append only file rewriting already in progress
Background append only file rewriting scheduled
Background append only file rewriting started
Unable to obtain the AOF file length. stat: %s
Background AOF rewrite terminated with success
Unable to open the temporary AOF produced by the child: %s
Error trying to flush the parent diff to the rewritten AOF: %s
Parent diff successfully flushed to the rewritten AOF (%lu bytes)
Error trying to rename the temporary AOF file: %s
Background AOF rewrite finished successfully
Background AOF rewrite signal handler took %lldus
Background AOF rewrite terminated with error
Background AOF rewrite terminated by signal %d
pubsub.c
channels
numsub
numpat
Unknown PUBSUB subcommand or wrong number of arguments for '%s'
MULTI calls can not be nested
DISCARD without MULTI
MULTI
EXEC without MULTI
clients != NULL
multi.c
WATCH inside MULTI is not allowed
eptr != NULL
debug.c
%.17g
"Unknown sorted set encoding"
"Unknown object type"
!!expire!!
segfault
assert
1 == 2
reload
Error trying to load the RDB dump
DB reloaded by DEBUG RELOAD
loadaof
Append Only File loaded by DEBUG LOADAOF
object
Value at:%p refcount:%d encoding:%s serializedlength:%lld lru:%d lru_seconds_idle:%lu
sdslen
Not an sds encoded string.
key_sds_len:%lld, key_sds_avail:%lld, val_sds_len:%lld, val_sds_avail:%lld
populate
key:%lu
value:%lu
digest
%02x
sleep
set-active-expire
error
Unknown DEBUG subcommand or wrong number of arguments for '%s'
=== ASSERTION FAILED ===
==> %s:%d '%s' is not true
=== ASSERTION FAILED CLIENT CONTEXT ===
client->flags = %d
client->fd = %d
client->argc = %d
Object type: %d, encoding: %d
client->argv[%d] = "%s" (refcount: %d)
Object type: %d
Object encoding: %d
Object refcount: %d
Object raw string len: %zu
Object raw string content: %s
List length: %d
Set size: %d
Hash size: %d
Sorted set size: %d
Skiplist level: %d
=== ASSERTION FAILED OBJECT CONTEXT ===
------------------------------------------------
!!! Software Failure. Press left mouse button to continue
Guru Meditation: %s #%s:%d
=== REDIS BUG REPORT START: Cut & paste starting from here ===
0123456789abcdef
%s (hexdump):
--- WATCHDOG TIMER EXPIRED ---
Sorry: no support for backtrace().
--------
desc
alpha
store
"Bad SORT type"
sort.c
"Unknown type"
j == vectorlen
1 != 1
One or more scores can't be converted into double
sop->type == REDIS_SORT_GET
sortstore
rdbSaveObjectType(payload,o)
migrate.c
rdbSaveObject(payload,o)
Target key name is busy.
Invalid TTL value, must be >= 0
DUMP payload version or checksum are wrong
Bad data format
+NOKEY
Can't connect to target node: %s
-IOERR error or timeout connecting to the client
rioWriteBulkCount(&cmd,'*',2)
SELECT
rioWriteBulkString(&cmd,"SELECT",6)
rioWriteBulkLongLong(&cmd,dbid)
rioWriteBulkCount(&cmd,'*',4)
RESTORE
rioWriteBulkString(&cmd,"RESTORE",7)
rioWriteBulkString(&cmd,c->argv[3]->ptr,sdslen(c->argv[3]->ptr))
rioWriteBulkLongLong(&cmd,ttl)
rioWriteBulkString(&cmd,payload.io.buffer.ptr, sdslen(payload.io.buffer.ptr))
Target instance replied with error: %s
-IOERR error or timeout writing to target instance
-IOERR error or timeout reading from target node
... (%d more arguments)
... (%lu more bytes)
reset
Unknown SLOWLOG subcommand or wrong # of args. Try GET, RESET, LEN.
%s: %d: %s
table
__redis__compare_helper
Please specify at least one argument for redis.call()
Lua redis() command arguments must be strings or integers
Wrong number of args calling Redis command From Lua script
Unknown Redis command called from Lua script
This Redis command is not allowed from scripts
Write commands not allowed after non deterministic commands
wrong number of arguments
wrong number or type of arguments
redis.log() requires two arguments or more.
First argument must be a number (log level).
Invalid debug level.
Lua slow script detected: still in execution after %lld milliseconds. You can try killing the script using the SCRIPT KILL command.
Lua script killed by user with SCRIPT KILL.
Script killed by user with SCRIPT KILL...
math
cjson
struct
cmsgpack
loadfile
local mt = {}
setmetatable(_G, mt)
mt.__newindex = function (t, n, v)
  if debug.getinfo(2) then
    local w = debug.getinfo(2, "S").what
    if w ~= "main" and w ~= "C" then
      error("Script attempted to create global variable '"..tostring(n).."'", 2)
    end
  end
  rawset(t, n, v)
mt.__index = function (t, n)
  if debug.getinfo(2) and debug.getinfo(2, "S").what ~= "C" then
    error("Script attempted to access unexisting global variable '"..tostring(n).."'", 2)
  return rawget(t, n)
@enable_strict_lua
call
pcall
LOG_DEBUG
LOG_VERBOSE
LOG_NOTICE
LOG_WARNING
sha1hex
error_reply
status_reply
random
randomseed
function __redis__compare_helper(a,b)
  if a == false then a = '' end
  if b == false then b = '' end
  return a<b
@cmp_func_def
function __redis__err__handler(err)
  local i = debug.getinfo(2,'nSl')
  if i and i.what == 'C' then
    i = debug.getinfo(3,'nSl')
  end
  if i then
    return i.source .. ':' .. i.currentline .. ': ' .. err
  else
    return err
  end
@err_handler_def
function 
 end
@user_script
Error compiling script (new function): %s
Error running script (new function): %s
scripting.c
Number of keys can't be greater than number of args
__redis__err__handler
!lua_isnil(lua,-1)
KEYS
ARGV
Error running script (call to %s): %s
script != NULL
EVAL
interval is empty
flush
load
-NOTBUSY No scripts in execution right now.
-UNKILLABLE Sorry the script already executed write commands against the dataset. You can either wait the script termination or kill the server in a hard way using the SHUTDOWN NOSAVE command.
Unknown SCRIPT subcommand or wrong # of args.
Fatal: Can't initialize Background Jobs.
Warning: can't mask SIGALRM in bio.c thread: %s
"Wrong job type in bioProcessBackgroundJobs()."
bio.c
Bio thread for job type #%d can be joined: %s
Bio thread for job type #%d terminated
r->read == rioFileIO.read
rio.c
Also check http://www.memtest86.com/ and http://pyropus.ca/software/memtester/
%s [%d]
*** MEMORY ADDRESSING ERROR: %p contains %lu
memtest_fill_random
memtest.c
(bytes & 4095) == 0
memtest_fill_value
memtest_compare
*** MEMORY ERROR DETECTED: %p != %p (%lu vs %lu)
Compare
Unable to allocate %zu megabytes: %s
Addressing test
Random fill
Solid fill
Checkerboard fill
Please keep the test running several minutes per GB of memory.
Your memory passed this test.
Please if you are still in doubt use the following two tools:
1) memtest86: http://www.memtest86.com/
2) memtester: http://pyropus.ca/software/memtester/
"End of redisBitpos() reached."
bitops.c
bit is not an integer or out of range
BITOP NOT must be called with a single source key.
The bit argument must be 1 or 0.
bit offset is not an integer or out of range
sentinel.c
Sentinel runid is %s
Sentinel started without a config file. Exiting...
Sentinel config file %s is not writable: %s. Exiting...
%s %s %s %d @ %s %s %d
%s %s %s %d
+monitor
%@ quorum %d
listLength(sentinel.scripts_queue) <= SENTINEL_SCRIPT_MAX_QUEUE
-script-error
%s %d %d
+script-child
-script-child
%ld %d %d
wait3() returned a pid (%ld) we can't find in our scripts execution queue!
-script-timeout
%s %ld
argv
flags
running
scheduled
run-time
run-delay
retry-num
leader
observer
flags & (SRI_MASTER|SRI_SLAVE|SRI_SENTINEL)
(flags & SRI_MASTER) || master != NULL
ri->flags & SRI_MASTER
ip || runid
+reset-master
+slave
Quorum must be 1 or greater.
Duplicated master name.
Can't resolve master instance hostname.
Invalid port number
down-after-milliseconds
No such master with specified name.
negative or zero time parameter.
failover-timeout
parallel-syncs
notification-script
Notification script seems non existing or non executable.
client-reconfig-script
Client reconfiguration script seems non existing or non executable.
auth-pass
current-epoch
config-epoch
leader-epoch
known-slave
Wrong hostname or port for slave.
known-sentinel
Wrong hostname or port for sentinel.
Unrecognized sentinel configuration statement.
sentinel monitor %s %s %d %d
sentinel down-after-milliseconds %s %ld
sentinel failover-timeout %s %ld
sentinel parallel-syncs %s %d
sentinel notification-script %s %s
sentinel client-reconfig-script %s %s
sentinel auth-pass %s %s
sentinel config-epoch %s %llu
sentinel leader-epoch %s %llu
sentinel known-slave %s %s %d
sentinel known-sentinel %s %s %d%s%s
sentinel current-epoch %llu
WARNING: Sentinel was not able to save the new configuration on disk!!!: %s
-pubsub-link
-cmd-link
%@ #%s
+pubsub-link
+cmd-link
AUTH %s
sentinel-%.8s-%s
CLIENT SETNAME %s
-cmd-link-reconnection
-pubsub-link-reconnection
SUBSCRIBE %s
__sentinel__:hello
run_id:
+reboot
port=
master_link_down_since_seconds
role:master
role:slave
master_host:
master_port:
master_link_status:
slave_priority:
slave_repl_offset:
+role-change
-role-change
%@ new reported role is %s
+promoted-slave
+failover-state-reconf-slaves
start
+convert-to-slave
+fix-slave-config
+slave-reconf-inprog
+slave-reconf-done
PONG
LOADING
MASTERDOWN
BUSY
SCRIPT KILL
-dup-sentinel
%@ #duplicate of %s:%d or %s
+sentinel
+new-epoch
%llu
+config-update-from
+switch-master
%s %s %d %s %d
message
%s,%d,%s,%llu,%s,%s,%d,%llu
PUBLISH %s %s
INFO
wait_start
select_slave
send_slaveof_noone
wait_promotion
reconf_slaves
update_config
name
runid
s_down,
o_down,
master,
slave,
sentinel,
disconnected,
master_down,
failover_in_progress,
promoted,
reconf_sent,
reconf_inprog,
reconf_done,
pending-commands
failover-state
last-ping-sent
last-ok-ping-reply
last-ping-reply
s-down-time
o-down-time
info-refresh
role-reported
role-reported-time
num-slaves
num-other-sentinels
quorum
master-link-down-time
master-link-status
master-host
master-port
slave-repl-offset
last-hello-message
voted-leader
voted-leader-epoch
No such master with that name
masters
slaves
sentinels
is-master-down-by-addr
get-master-addr-by-name
failover
-INPROG Failover already in progress
-NOGOODSLAVE No suitable slave to promote
Executing user requested FAILOVER of '%s'
pending-scripts
Invalid quorum
Invalid IP address specified
Duplicated master name
Unspecified error adding the instance
remove
-monitor
Unknown sentinel subcommand '%s'
Wrong number of arguments for 'sentinel %s'
# Sentinel
sentinel_masters:%lu
sentinel_tilt:%d
sentinel_running_scripts:%d
sentinel_scripts_queue_length:%ld
odown
sdown
master%d:name=%s,status=%s,address=%s:%d,slaves=%lu,sentinels=%lu
Notification script seems non existing or non executable
Client reconfiguration script seems non existing or non executable
Unknown option '%s' for SENTINEL SET
+set
%@ %s %s
Invalid argument '%s' for SENTINEL SET '%s'
Only HELLO messages are accepted by Sentinel instances.
+sdown
-sdown
+odown
%@ #quorum %d/%d
-odown
%s voted for %s %llu
SENTINEL is-master-down-by-addr %s %s %llu %s
+vote-for-leader
%s %llu
master->flags & (SRI_O_DOWN|SRI_FAILOVER_IN_PROGRESS)
SLAVEOF %s %s
CONFIG REWRITE
CLIENT KILL TYPE normal
EXEC
master->flags & SRI_MASTER
+try-failover
Next failover delay: I will not start a failover before %s
-failover-abort-not-elected
+elected-leader
+failover-state-select-slave
-failover-abort-no-good-slave
+selected-slave
+failover-state-send-slaveof-noone
-failover-abort-slave-timeout
+failover-state-wait-promotion
+failover-end-for-timeout
+failover-end
+slave-reconf-sent-be
-slave-reconf-sent-timeout
+slave-reconf-sent
ri->flags & SRI_FAILOVER_IN_PROGRESS
ri->failover_state <= SENTINEL_FAILOVER_STATE_WAIT_PROMOTION
-tilt
#tilt mode exited
+tilt
#tilt mode entered
__keyspace@
__keyevent@
dense_retval == 1
hyperloglog.c
"Unknown HyperLogLog encoding in hllCount()"
-WRONGTYPE Key is not a valid HyperLogLog string value.
TESTFAILED Register %d should be %d but is %d
TESTFAILED sparse encoding not used
TESTFAILED dense/sparse disagree
TESTFAILED Too big error. card:%llu abserr:%llu
The specified key does not exist
getreg
decode
HLL encoding is not sparse
z:%d 
Z:%d 
v:%d,%d 
dense
sparse
todense
Unknown PFDEBUG subcommand '%s'
Wrong number of arguments for the '%s' subcommand
-INVALIDOBJ Corrupted HLL object detected
getsockopt(SO_ERROR)
setsockopt(SO_RCVTIMEO)
setsockopt(SO_SNDTIMEO)
%s: 
Can't get addr: %s
Can't bind socket: %s
Can't create socket: %s
setsockopt(TCP_NODELAY)
fcntl(F_GETFL)
fcntl(F_SETFL)
poll(2)
redisReaderFeed
hiredis.c
r->buf != NULL
eEfFgGaA
$%zu
redisvFormatCommand
pos == totlen
redisFormatCommandArgv
__redisSetError
type == REDIS_ERR_IO
Server closed the connection
Out of memory
createStringObject
task->type == REDIS_REPLY_ERROR || task->type == REDIS_REPLY_STATUS || task->type == REDIS_REPLY_STRING
parent->type == REDIS_REPLY_ARRAY
createArrayObject
createIntegerObject
createNilObject
processItem
Protocol error, got %s as reply type byte
"\%c"
"\n"
"\r"
"\t"
"\a"
"\b"
"%c"
"\x%02x"
moveToNextTask
prv->type == REDIS_REPLY_ARRAY
cur->idx < prv->elements
No support for nested multi bulk replies with depth > 7
redisProcessCallbacks
async.c
(c->flags & REDIS_SUBSCRIBED || c->flags & REDIS_MONITORING)
__redisAsyncDisconnect
__redisShiftCallback(&ac->replies,NULL) == REDIS_ERR
__redisGetSubscribeCallback
reply->elements >= 2
reply->element[0]->type == REDIS_REPLY_STRING
reply->element[1]->type == REDIS_REPLY_STRING
reply->element[2]->type == REDIS_REPLY_INTEGER
__redisAsyncCommand
subscribe
unsubscribe
monitor
nextArgument
dictExpand
./dict.c
ht->used == 0
no calling environment
no value
function or expression too complex
control structure too long
code size overflow
attempt to %s %s '%s' (a %s value)
attempt to %s a %s value
concatenate
perform arithmetic on
attempt to compare two %s values
attempt to compare %s with %s
(*temporary)
tail
=(tail call)
=[C]
main
local
global
field
upvalue
%s:%d: %s
error in error handling
C stack overflow
cannot resume non-suspended coroutine
attempt to yield across metamethod/C-call boundary
stack overflow
break
else
elseif
repeat
then
until
while
<number>
<name>
<string>
<eof>
char(%d)
%s near '%s'
lexical element too long
invalid long string delimiter
chunk has too many lines
unfinished long string
unfinished long comment
nesting of [[...]] is deprecated
unfinished string
escape sequence too large
malformed number
memory allocation error: block too big
(null)
[string "
MOVE
LOADK
LOADBOOL
LOADNIL
GETUPVAL
GETGLOBAL
GETTABLE
SETGLOBAL
SETUPVAL
SETTABLE
NEWTABLE
SELF
CONCAT
TEST
TESTSET
CALL
TAILCALL
RETURN
FORLOOP
FORPREP
TFORLOOP
SETLIST
CLOSE
CLOSURE
VARARG
'%s' expected
chunk has too many syntax levels
cannot use '...' outside a vararg function
items in a constructor
main function has more than %d %s
function at line %d has more than %d %s
self
local variables
too many local variables
<name> or '...' expected
constant table overflow
unexpected symbol
upvalues
ambiguous syntax (function call x new statement)
function arguments expected
'%s' expected (to close '%s' at line %d)
'=' or 'in' expected
(for index)
(for limit)
(for step)
(for generator)
(for state)
(for control)
no loop to break
syntax error
variables in assignment
not enough memory
table index is nil
table index is NaN
invalid key to 'next'
table overflow
boolean
userdata
number
function
thread
proto
upval
__newindex
__eq
__add
__sub
__mul
__div
__mod
__pow
__unm
__len
__lt
__le
__concat
__call
binary string
bad header
unexpected end
%s: %s in precompiled chunk
code too deep
bad code
bad integer
bad constant
%.14g
index
loop in gettable
loop in settable
string length overflow
get length of
'for' initial value must be a number
'for' limit must be a number
'for' step must be a number
BUG: Invalid string increment
strbuf(%lx) resize: %d => %d
BUG: Unable to convert number
BUG: length of formatted string changed
strbuf(%lx) reallocs: %d, length: %d, size: %d
BUG: Invalid strbuf length requested
bad argument #%d (%s)
method
calling '%s' on bad self (%s)
bad argument #%d to '%s' (%s)
%s expected, got %s
%s:%d: 
invalid option '%s'
stack overflow (%s)
value expected
_LOADED
name conflict for module '%s'
=stdin
open
reopen
read
cannot %s %s: %s
PANIC: unprotected error in call to Lua API (%s)
coroutine
Lua 5.1
_VERSION
ipairs
pairs
__mode
newproxy
collectgarbage
dofile
gcinfo
getfenv
getmetatable
loadstring
next
print
rawequal
rawget
rawset
setfenv
setmetatable
tonumber
tostring
unpack
xpcall
assertion failed!
stop
restart
collect
step
setpause
setstepmul
level must be non-negative
invalid level
no function environment for tail call at level %d
__metatable
=(load)
too many nested functions
reader function must return a string
'tostring' must return a string to 'print'
index out of range
'setfenv' cannot change environment of given object
nil or table expected
cannot change a protected metatable
base out of range
__tostring
true
false
%s: %p
too many results to unpack
boolean or proxy expected
create
resume
status
wrap
yield
Lua function expected
coroutine expected
too many arguments to resume
cannot resume %s coroutine
too many results to resume
suspended
dead
gethook
getinfo
getlocal
getregistry
getupvalue
sethook
setlocal
setupvalue
traceback
lua_debug> 
cont
=(debug command)
external hook
return
line
tail return
flnSu
function or level expected
invalid option
source
short_src
linedefined
lastlinedefined
what
currentline
nups
namewhat
activelines
func
level out of range
stack traceback:
 in function '%s'
 in main chunk
 in function <%s:%d>
huge
fmod
acos
asin
atan2
atan
ceil
cosh
floor
frexp
ldexp
log10
modf
sinh
sqrt
tanh
concat
foreach
foreachi
getn
maxn
insert
setn
invalid value (%s) at index %d in table for 'concat'
wrong number of arguments to 'insert'
'setn' is obsolete
invalid order function for sorting
gmatch
gfind
byte
char
find
format
gsub
lower
reverse
upper
string slice too long
invalid value
unable to dump given function
^$*+?.([%-
missing '[' after '%%f' in pattern
too many captures
invalid pattern capture
unbalanced pattern
malformed pattern (ends with '%%')
malformed pattern (missing ']')
invalid capture index
unfinished capture
invalid option '%%%c' to 'format'
invalid format (repeated flags)
invalid format (width or precision too long)
\000
'string.gfind' was renamed to 'string.gmatch'
string/function/table expected
invalid replacement value (a %s)
__index
encode
encode_sparse_array
encode_max_depth
encode_number_precision
encode_keep_buffer
refuse_invalid_numbers
null
1.0.3
version
expected 1 argument
BUG: Unable to fetch CJSON configuration
type not supported
\u0000
\u0001
\u0002
\u0003
\u0004
\u0005
\u0006
\u0007
\u000b
\u000e
\u000f
\u0010
\u0011
\u0012
\u0013
\u0014
\u0015
\u0016
\u0017
\u0018
\u0019
\u001a
\u001b
\u001c
\u001d
\u001e
\u001f
\u007f
must not be NaN or Inf
excessively sparse array
Cannot serialise, excessive nesting (%d)
table key must be a number or string
Cannot serialise %s: %s
JSON parser does not support UTF-16 or UTF-32
found too many arguments
the end
invalid token
invalid number
unexpected end of string
invalid unicode escape code
invalid escape code
value
object key string
colon
comma or object end
Too many nested data structures
comma or array end
Expected %s but found %s at character %d
T_OBJ_BEGIN
T_OBJ_END
T_ARR_BEGIN
T_ARR_END
T_STRING
T_NUMBER
T_BOOLEAN
T_NULL
T_COLON
T_COMMA
T_END
T_WHITESPACE
T_ERROR
T_UNKNOWN
expected integer >= 0
expected boolean
expected positive integer
expected integer between 1 and 14
%%.%dg
both
__gc
size
string too short
integral size %d is larger than limit of %d
alignment %d is not a power of 2
invalid format option '%c'
data string too short
too many results
format `c0' needs a previous size
unfinished string in data
option 's' has no fixed size
option 'c0' has no fixed size
lua-cmsgpack 0.3.0
Copyright (C) 2012, Salvatore Sanfilippo
_COPYRIGHT
MessagePack C implementation for Lua
_DESCRIPTION
pack
MessagePack decoding needs a string as input.
Missing bytes in input.
Bad data format in input.
Extra bytes in input.
on not permitted-ERR operation n
                
+tPOu
w!X|
HY{'
{VI!
D"A/oyu
w!hy
dsw
QguI
aco-nz
6RtcZO"
H$BQ
XS&Y+
s3o\
\D2%4
u<~{
,6a<
;(uu
z`%1Is}
KM^bM
='2T
URdN
.wM^
p&S@
!Y%E
>?Wn
sVwES
-oX"'
+7a_
"s7$
Rg|/
)UUUUUUUU
33333333
wn_since_secondsmaster_link_downter_link_status:master_link_statslave_repl_offset:
?diouxX
$Lua: Lua 5.1.5 Copyright (C) 1994-2012 Lua.org, PUC-Rio $
$Authors: R. Ierusalimschy, L. H. de Figueiredo & W. Celes $
$URL: www.lua.org $
................
`qT`Pql1
<Tl||||||```h"
